mytools/__init__.py
mytools/cmap.py
mytools/epoch.py
mytools/fbpic.py
mytools/laser.py
mytools/plasma.py
mytools/plot.py
mytools/smilei.py
xsgeng_tools-0.5.0.dist-info/licenses/LICENSE
xsgeng_tools-0.5.0.dist-info/METADATA
xsgeng_tools-0.5.0.dist-info/WHEEL
xsgeng_tools-0.5.0.dist-info/top_level.txt
xsgeng_tools-0.5.0.dist-info/RECORD
