Metadata-Version: 2.4
Name: xsgeng-tools
Version: 0.5.0
Summary: my tools for pic
Author-email: xsgeng <xsgeng@siom.ac.cn>
License:                     GNU GENERAL PUBLIC LICENSE
Project-URL: Homepage, https://github.com/xsgeng/mytools
Keywords: Plasma Physics,Strong field
Classifier: Development Status :: 3 - Alpha
Classifier: Intended Audience :: Science/Research
Requires-Python: >=3.7
License-File: LICENSE
Requires-Dist: numpy
Requires-Dist: scipy
Dynamic: license-file
